{
    "path": "../output/imgs/deutsche-frauen/71.jpeg",
    "search_query": "deutsche-frauen",
    "position": 71,
    "label_annotations": [
        {
            "mid": "/m/03q69",
            "score": 0.9836969375610352,
            "topicality": 0.9836969375610352,
            "description": "Hair"
        },
        {
            "mid": "/m/06pj2k",
            "score": 0.9703880548477173,
            "topicality": 0.9703880548477173,
            "description": "Lip"
        },
        {
            "mid": "/m/0f9swq",
            "score": 0.9661365151405334,
            "topicality": 0.9661365151405334,
            "description": "Chin"
        },
        {
            "mid": "/m/027n3_",
            "score": 0.9428966045379639,
            "topicality": 0.9428966045379639,
            "description": "Eyebrow"
        },
        {
            "mid": "/m/03f52z",
            "score": 0.9285533428192139,
            "topicality": 0.9285533428192139,
            "description": "Eyelash"
        },
        {
            "mid": "/m/032tl",
            "score": 0.8849974870681763,
            "topicality": 0.8849974870681763,
            "description": "Fashion"
        },
        {
            "mid": "/g/1tr17zw8",
            "score": 0.8827386498451233,
            "topicality": 0.8827386498451233,
            "description": "Flash photography"
        },
        {
            "mid": "/m/02qp_b",
            "score": 0.8687187433242798,
            "topicality": 0.8687187433242798,
            "description": "Makeover"
        },
        {
            "mid": "/m/0lxkm",
            "score": 0.8548062443733215,
            "topicality": 0.8548062443733215,
            "description": "Iris"
        },
        {
            "mid": "/m/03_pfn",
            "score": 0.8467885851860046,
            "topicality": 0.8467885851860046,
            "description": "Liver"
        }
    ],
    "safe_search_annotations": {
        "adult": {
            "likelihood": "VERY_UNLIKELY"
        },
        "racy": {
            "likelihood": "UNLIKELY"
        },
        "spoof": {
            "likelihood": "VERY_UNLIKELY"
        },
        "medical": {
            "likelihood": "UNLIKELY"
        },
        "violence": {
            "likelihood": "VERY_UNLIKELY"
        }
    }
}