{
    "path": "../output/imgs/mujeres-colombianas/52.jpeg",
    "search_query": "mujeres-colombianas",
    "position": 52,
    "label_annotations": [
        {
            "mid": "/m/09j5n",
            "score": 0.9843506813049316,
            "topicality": 0.9843506813049316,
            "description": "Footwear"
        },
        {
            "mid": "/m/03q69",
            "score": 0.9826229214668274,
            "topicality": 0.9826229214668274,
            "description": "Hair"
        },
        {
            "mid": "/m/019nj4",
            "score": 0.9803760647773743,
            "topicality": 0.9803760647773743,
            "description": "Smile"
        },
        {
            "mid": "/m/01dvt1",
            "score": 0.9772205948829651,
            "topicality": 0.9772205948829651,
            "description": "Joint"
        },
        {
            "mid": "/m/06z04",
            "score": 0.974523663520813,
            "topicality": 0.974523663520813,
            "description": "Skin"
        },
        {
            "mid": "/m/06rrc",
            "score": 0.969418466091156,
            "topicality": 0.969418466091156,
            "description": "Shoe"
        },
        {
            "mid": "/m/01ssh5",
            "score": 0.9397854804992676,
            "topicality": 0.9397854804992676,
            "description": "Shoulder"
        },
        {
            "mid": "/m/035r7c",
            "score": 0.9351921081542969,
            "topicality": 0.9351921081542969,
            "description": "Leg"
        },
        {
            "mid": "/m/068mqj",
            "score": 0.9007357954978943,
            "topicality": 0.9007357954978943,
            "description": "Automotive design"
        },
        {
            "mid": "/m/032tl",
            "score": 0.8851510286331177,
            "topicality": 0.8851510286331177,
            "description": "Fashion"
        }
    ],
    "safe_search_annotations": {
        "adult": {
            "likelihood": "VERY_UNLIKELY"
        },
        "racy": {
            "likelihood": "UNLIKELY"
        },
        "spoof": {
            "likelihood": "VERY_UNLIKELY"
        },
        "medical": {
            "likelihood": "UNLIKELY"
        },
        "violence": {
            "likelihood": "VERY_UNLIKELY"
        }
    }
}