{
    "path": "../output/imgs/argentinian-women/87.jpeg",
    "search_query": "argentinian-women",
    "position": 87,
    "label_annotations": [
        {
            "mid": "/m/0k0pj",
            "score": 0.9842155575752258,
            "topicality": 0.9842155575752258,
            "description": "Nose"
        },
        {
            "mid": "/m/0283dt1",
            "score": 0.9815875291824341,
            "topicality": 0.9815875291824341,
            "description": "Mouth"
        },
        {
            "mid": "/m/06pj2k",
            "score": 0.9790182113647461,
            "topicality": 0.9790182113647461,
            "description": "Lip"
        },
        {
            "mid": "/m/014sv8",
            "score": 0.9743300676345825,
            "topicality": 0.9743300676345825,
            "description": "Eye"
        },
        {
            "mid": "/m/09q2t",
            "score": 0.9743174910545349,
            "topicality": 0.9743174910545349,
            "description": "Brown"
        },
        {
            "mid": "/m/0ds4x",
            "score": 0.9741173982620239,
            "topicality": 0.9741173982620239,
            "description": "Hairstyle"
        },
        {
            "mid": "/m/06z04",
            "score": 0.9718893766403198,
            "topicality": 0.9718893766403198,
            "description": "Skin"
        },
        {
            "mid": "/m/0f9swq",
            "score": 0.9693230986595154,
            "topicality": 0.9693230986595154,
            "description": "Chin"
        },
        {
            "mid": "/m/025kyy",
            "score": 0.9681845307350159,
            "topicality": 0.9681845307350159,
            "description": "Forehead"
        },
        {
            "mid": "/m/03f52z",
            "score": 0.9650818705558777,
            "topicality": 0.9650818705558777,
            "description": "Eyelash"
        }
    ],
    "safe_search_annotations": {
        "adult": {
            "likelihood": "VERY_UNLIKELY"
        },
        "racy": {
            "likelihood": "UNLIKELY"
        },
        "spoof": {
            "likelihood": "VERY_UNLIKELY"
        },
        "medical": {
            "likelihood": "VERY_UNLIKELY"
        },
        "violence": {
            "likelihood": "VERY_UNLIKELY"
        }
    }
}