{
    "path": "../output/imgs/argentinian-women/18.jpeg",
    "search_query": "argentinian-women",
    "position": 18,
    "label_annotations": [
        {
            "mid": "/m/09j2d",
            "score": 0.9924489855766296,
            "topicality": 0.9924489855766296,
            "description": "Clothing"
        },
        {
            "mid": "/m/0k0pj",
            "score": 0.9841269850730896,
            "topicality": 0.9841269850730896,
            "description": "Nose"
        },
        {
            "mid": "/m/0283dt1",
            "score": 0.9793767333030701,
            "topicality": 0.9793767333030701,
            "description": "Mouth"
        },
        {
            "mid": "/m/06pj2k",
            "score": 0.9790174961090088,
            "topicality": 0.9790174961090088,
            "description": "Lip"
        },
        {
            "mid": "/m/037p5b",
            "score": 0.9780845642089844,
            "topicality": 0.9780845642089844,
            "description": "Cheek"
        },
        {
            "mid": "/m/0ds4x",
            "score": 0.9740415215492249,
            "topicality": 0.9740415215492249,
            "description": "Hairstyle"
        },
        {
            "mid": "/m/014sv8",
            "score": 0.9725388288497925,
            "topicality": 0.9725388288497925,
            "description": "Eye"
        },
        {
            "mid": "/m/0f9swq",
            "score": 0.9690437912940979,
            "topicality": 0.9690437912940979,
            "description": "Chin"
        },
        {
            "mid": "/m/025kyy",
            "score": 0.9681841135025024,
            "topicality": 0.9681841135025024,
            "description": "Forehead"
        },
        {
            "mid": "/m/027n3_",
            "score": 0.9639065861701965,
            "topicality": 0.9639065861701965,
            "description": "Eyebrow"
        }
    ],
    "safe_search_annotations": {
        "adult": {
            "likelihood": "VERY_UNLIKELY"
        },
        "racy": {
            "likelihood": "VERY_UNLIKELY"
        },
        "spoof": {
            "likelihood": "VERY_UNLIKELY"
        },
        "medical": {
            "likelihood": "UNLIKELY"
        },
        "violence": {
            "likelihood": "VERY_UNLIKELY"
        }
    }
}