{
    "path": "../output/imgs/bulgarian-women/55.jpeg",
    "search_query": "bulgarian-women",
    "position": 55,
    "label_annotations": [
        {
            "mid": "/m/0hgr6",
            "score": 0.968787670135498,
            "topicality": 0.968787670135498,
            "description": "Denim"
        },
        {
            "mid": "/m/01ssh5",
            "score": 0.9651734232902527,
            "topicality": 0.9651734232902527,
            "description": "Shoulder"
        },
        {
            "mid": "/m/0fly7",
            "score": 0.9606785774230957,
            "topicality": 0.9606785774230957,
            "description": "Jeans"
        },
        {
            "mid": "/j/3gbwgn",
            "score": 0.9382697939872742,
            "topicality": 0.9382697939872742,
            "description": "People in nature"
        },
        {
            "mid": "/m/078qz",
            "score": 0.9339722990989685,
            "topicality": 0.9339722990989685,
            "description": "Summer"
        },
        {
            "mid": "/m/012yh1",
            "score": 0.9315227270126343,
            "topicality": 0.9315227270126343,
            "description": "Style"
        },
        {
            "mid": "/m/06z0n",
            "score": 0.9140260219573975,
            "topicality": 0.9140260219573975,
            "description": "Sunlight"
        },
        {
            "mid": "/m/01f43",
            "score": 0.9053694605827332,
            "topicality": 0.9053694605827332,
            "description": "Beauty"
        },
        {
            "mid": "/m/031974",
            "score": 0.9034242033958435,
            "topicality": 0.9034242033958435,
            "description": "Waist"
        },
        {
            "mid": "/m/032tl",
            "score": 0.8879921436309814,
            "topicality": 0.8879921436309814,
            "description": "Fashion"
        }
    ],
    "safe_search_annotations": {
        "adult": {
            "likelihood": "VERY_UNLIKELY"
        },
        "racy": {
            "likelihood": "UNLIKELY"
        },
        "spoof": {
            "likelihood": "VERY_UNLIKELY"
        },
        "medical": {
            "likelihood": "UNLIKELY"
        },
        "violence": {
            "likelihood": "VERY_UNLIKELY"
        }
    }
}