{
    "path": "../output/imgs/chilean-women/78.jpeg",
    "search_query": "chilean-women",
    "position": 78,
    "label_annotations": [
        {
            "mid": "/m/03q69",
            "score": 0.9894317984580994,
            "topicality": 0.9894317984580994,
            "description": "Hair"
        },
        {
            "mid": "/m/0dzct",
            "score": 0.9891619682312012,
            "topicality": 0.9891619682312012,
            "description": "Face"
        },
        {
            "mid": "/m/04hgtk",
            "score": 0.9880419969558716,
            "topicality": 0.9880419969558716,
            "description": "Head"
        },
        {
            "mid": "/m/0k0pj",
            "score": 0.9839450716972351,
            "topicality": 0.9839450716972351,
            "description": "Nose"
        },
        {
            "mid": "/m/019nj4",
            "score": 0.9795199036598206,
            "topicality": 0.9795199036598206,
            "description": "Smile"
        },
        {
            "mid": "/m/0283dt1",
            "score": 0.9794498085975647,
            "topicality": 0.9794498085975647,
            "description": "Mouth"
        },
        {
            "mid": "/m/09g5pq",
            "score": 0.9772156476974487,
            "topicality": 0.9772156476974487,
            "description": "People"
        },
        {
            "mid": "/m/06fvc",
            "score": 0.9578635096549988,
            "topicality": 0.9578635096549988,
            "description": "Red"
        },
        {
            "mid": "/m/016pp7",
            "score": 0.9474340081214905,
            "topicality": 0.9474340081214905,
            "description": "Happy"
        },
        {
            "mid": "/m/01k74n",
            "score": 0.9344747066497803,
            "topicality": 0.9344747066497803,
            "description": "Facial expression"
        }
    ],
    "safe_search_annotations": {
        "adult": {
            "likelihood": "VERY_UNLIKELY"
        },
        "racy": {
            "likelihood": "VERY_UNLIKELY"
        },
        "spoof": {
            "likelihood": "VERY_UNLIKELY"
        },
        "medical": {
            "likelihood": "VERY_UNLIKELY"
        },
        "violence": {
            "likelihood": "VERY_UNLIKELY"
        }
    }
}