{
    "path": "../output/imgs/cuban-women/59.jpeg",
    "search_query": "cuban-women",
    "position": 59,
    "label_annotations": [
        {
            "mid": "/m/09j2d",
            "score": 0.9923083186149597,
            "topicality": 0.9923083186149597,
            "description": "Clothing"
        },
        {
            "mid": "/m/03ktm1",
            "score": 0.9874946475028992,
            "topicality": 0.9874946475028992,
            "description": "Body of water"
        },
        {
            "mid": "/m/0ds99lh",
            "score": 0.9792434573173523,
            "topicality": 0.9792434573173523,
            "description": "Fun"
        },
        {
            "mid": "/m/01gmv2",
            "score": 0.975639283657074,
            "topicality": 0.975639283657074,
            "description": "Brassiere"
        },
        {
            "mid": "/m/06z04",
            "score": 0.9702714681625366,
            "topicality": 0.9702714681625366,
            "description": "Skin"
        },
        {
            "mid": "/j/148skd",
            "score": 0.9632052183151245,
            "topicality": 0.9632052183151245,
            "description": "People on beach"
        },
        {
            "mid": "/m/01gkx_",
            "score": 0.9578858017921448,
            "topicality": 0.9578858017921448,
            "description": "Swimwear"
        },
        {
            "mid": "/m/04g3r",
            "score": 0.9575886726379395,
            "topicality": 0.9575886726379395,
            "description": "Leisure"
        },
        {
            "mid": "/m/07bxq",
            "score": 0.9493590593338013,
            "topicality": 0.9493590593338013,
            "description": "Tourism"
        },
        {
            "mid": "/m/01g8j",
            "score": 0.9492201805114746,
            "topicality": 0.9492201805114746,
            "description": "Bikini"
        }
    ],
    "safe_search_annotations": {
        "adult": {
            "likelihood": "UNLIKELY"
        },
        "racy": {
            "likelihood": "VERY_LIKELY"
        },
        "spoof": {
            "likelihood": "VERY_UNLIKELY"
        },
        "medical": {
            "likelihood": "UNLIKELY"
        },
        "violence": {
            "likelihood": "VERY_UNLIKELY"
        }
    }
}