{
    "path": "../output/imgs/dutch-women/58.jpeg",
    "search_query": "dutch-women",
    "position": 58,
    "label_annotations": [
        {
            "mid": "/m/03q69",
            "score": 0.9900942444801331,
            "topicality": 0.9900942444801331,
            "description": "Hair"
        },
        {
            "mid": "/m/0dzct",
            "score": 0.9886342883110046,
            "topicality": 0.9886342883110046,
            "description": "Face"
        },
        {
            "mid": "/m/0k0pj",
            "score": 0.9835904836654663,
            "topicality": 0.9835904836654663,
            "description": "Nose"
        },
        {
            "mid": "/m/019nj4",
            "score": 0.9796302914619446,
            "topicality": 0.9796302914619446,
            "description": "Smile"
        },
        {
            "mid": "/m/014sv8",
            "score": 0.9720513820648193,
            "topicality": 0.9720513820648193,
            "description": "Eye"
        },
        {
            "mid": "/m/04dr76w",
            "score": 0.9610294699668884,
            "topicality": 0.9610294699668884,
            "description": "Bottle"
        },
        {
            "mid": "/m/0271t",
            "score": 0.958021879196167,
            "topicality": 0.958021879196167,
            "description": "Drink"
        },
        {
            "mid": "/m/089mxq",
            "score": 0.9575361013412476,
            "topicality": 0.9575361013412476,
            "description": "Glass bottle"
        },
        {
            "mid": "/m/0lqk",
            "score": 0.953143298625946,
            "topicality": 0.953143298625946,
            "description": "Alcohol"
        },
        {
            "mid": "/m/016pp7",
            "score": 0.9462886452674866,
            "topicality": 0.9462886452674866,
            "description": "Happy"
        }
    ],
    "safe_search_annotations": {
        "adult": {
            "likelihood": "VERY_UNLIKELY"
        },
        "racy": {
            "likelihood": "VERY_UNLIKELY"
        },
        "spoof": {
            "likelihood": "UNLIKELY"
        },
        "medical": {
            "likelihood": "VERY_UNLIKELY"
        },
        "violence": {
            "likelihood": "VERY_UNLIKELY"
        }
    }
}