{
    "path": "../output/imgs/filipino-women/70.jpeg",
    "search_query": "filipino-women",
    "position": 70,
    "label_annotations": [
        {
            "mid": "/m/03ktm1",
            "score": 0.9877392053604126,
            "topicality": 0.9877392053604126,
            "description": "Body of water"
        },
        {
            "mid": "/m/02c9_23",
            "score": 0.9741334915161133,
            "topicality": 0.9741334915161133,
            "description": "Coastal and oceanic landforms"
        },
        {
            "mid": "/m/068jd",
            "score": 0.9558185338973999,
            "topicality": 0.9558185338973999,
            "description": "Photograph"
        },
        {
            "mid": "/m/07bxq",
            "score": 0.9420371651649475,
            "topicality": 0.9420371651649475,
            "description": "Tourism"
        },
        {
            "mid": "/m/05kq4",
            "score": 0.937881350517273,
            "topicality": 0.937881350517273,
            "description": "Ocean"
        },
        {
            "mid": "/m/078qz",
            "score": 0.9362349510192871,
            "topicality": 0.9362349510192871,
            "description": "Summer"
        },
        {
            "mid": "/m/099fz",
            "score": 0.9359492659568787,
            "topicality": 0.9359492659568787,
            "description": "Sand"
        },
        {
            "mid": "/m/01lxd",
            "score": 0.9151665568351746,
            "topicality": 0.9151665568351746,
            "description": "Coast"
        },
        {
            "mid": "/m/01d40f",
            "score": 0.9146192669868469,
            "topicality": 0.9146192669868469,
            "description": "Dress"
        },
        {
            "mid": "/m/0b3yr",
            "score": 0.9115837216377258,
            "topicality": 0.9115837216377258,
            "description": "Beach"
        }
    ],
    "safe_search_annotations": {
        "adult": {
            "likelihood": "VERY_UNLIKELY"
        },
        "racy": {
            "likelihood": "UNLIKELY"
        },
        "spoof": {
            "likelihood": "VERY_UNLIKELY"
        },
        "medical": {
            "likelihood": "VERY_UNLIKELY"
        },
        "violence": {
            "likelihood": "VERY_UNLIKELY"
        }
    }
}