{
    "path": "../output/imgs/finnish-women/39.jpeg",
    "search_query": "finnish-women",
    "position": 39,
    "label_annotations": [
        {
            "mid": "/m/06pj2k",
            "score": 0.9790162444114685,
            "topicality": 0.9790162444114685,
            "description": "Lip"
        },
        {
            "mid": "/m/0ds4x",
            "score": 0.9739137887954712,
            "topicality": 0.9739137887954712,
            "description": "Hairstyle"
        },
        {
            "mid": "/m/01ssh5",
            "score": 0.9652032852172852,
            "topicality": 0.9652032852172852,
            "description": "Shoulder"
        },
        {
            "mid": "/m/03f52z",
            "score": 0.9256970286369324,
            "topicality": 0.9256970286369324,
            "description": "Eyelash"
        },
        {
            "mid": "/m/078qz",
            "score": 0.9220410585403442,
            "topicality": 0.9220410585403442,
            "description": "Summer"
        },
        {
            "mid": "/m/01f43",
            "score": 0.9088834524154663,
            "topicality": 0.9088834524154663,
            "description": "Beauty"
        },
        {
            "mid": "/m/077p0h",
            "score": 0.9064058661460876,
            "topicality": 0.9064058661460876,
            "description": "Sleeveless shirt"
        },
        {
            "mid": "/m/0408t8_",
            "score": 0.893171489238739,
            "topicality": 0.893171489238739,
            "description": "Street fashion"
        },
        {
            "mid": "/m/02ksmb",
            "score": 0.8686590194702148,
            "topicality": 0.8686590194702148,
            "description": "Brown hair"
        },
        {
            "mid": "/m/02pd__z",
            "score": 0.8650627136230469,
            "topicality": 0.8650627136230469,
            "description": "Long hair"
        }
    ],
    "safe_search_annotations": {
        "adult": {
            "likelihood": "VERY_UNLIKELY"
        },
        "racy": {
            "likelihood": "UNLIKELY"
        },
        "spoof": {
            "likelihood": "VERY_UNLIKELY"
        },
        "medical": {
            "likelihood": "UNLIKELY"
        },
        "violence": {
            "likelihood": "VERY_UNLIKELY"
        }
    }
}