{
    "path": "../output/imgs/guyanese-women/2.jpeg",
    "search_query": "guyanese-women",
    "position": 2,
    "label_annotations": [
        {
            "mid": "/m/0k0pj",
            "score": 0.9835832118988037,
            "topicality": 0.9835832118988037,
            "description": "Nose"
        },
        {
            "mid": "/m/06pj2k",
            "score": 0.9790181517601013,
            "topicality": 0.9790181517601013,
            "description": "Lip"
        },
        {
            "mid": "/m/037p5b",
            "score": 0.9788221716880798,
            "topicality": 0.9788221716880798,
            "description": "Cheek"
        },
        {
            "mid": "/m/09q2t",
            "score": 0.977050244808197,
            "topicality": 0.977050244808197,
            "description": "Brown"
        },
        {
            "mid": "/m/0ds4x",
            "score": 0.9741198420524597,
            "topicality": 0.9741198420524597,
            "description": "Hairstyle"
        },
        {
            "mid": "/m/014sv8",
            "score": 0.9728555679321289,
            "topicality": 0.9728555679321289,
            "description": "Eye"
        },
        {
            "mid": "/m/06z04",
            "score": 0.9705541133880615,
            "topicality": 0.9705541133880615,
            "description": "Skin"
        },
        {
            "mid": "/m/0f9swq",
            "score": 0.969329833984375,
            "topicality": 0.969329833984375,
            "description": "Chin"
        },
        {
            "mid": "/m/025kyy",
            "score": 0.9681846499443054,
            "topicality": 0.9681846499443054,
            "description": "Forehead"
        },
        {
            "mid": "/m/027n3_",
            "score": 0.9639071226119995,
            "topicality": 0.9639071226119995,
            "description": "Eyebrow"
        }
    ],
    "safe_search_annotations": {
        "adult": {
            "likelihood": "VERY_UNLIKELY"
        },
        "racy": {
            "likelihood": "UNLIKELY"
        },
        "spoof": {
            "likelihood": "VERY_UNLIKELY"
        },
        "medical": {
            "likelihood": "VERY_UNLIKELY"
        },
        "violence": {
            "likelihood": "UNLIKELY"
        }
    }
}