{
    "path": "../output/imgs/iranian-women/44.jpeg",
    "search_query": "iranian-women",
    "position": 44,
    "label_annotations": [
        {
            "mid": "/m/0dzct",
            "score": 0.9888941049575806,
            "topicality": 0.9888941049575806,
            "description": "Face"
        },
        {
            "mid": "/m/0k0pj",
            "score": 0.9843997955322266,
            "topicality": 0.9843997955322266,
            "description": "Nose"
        },
        {
            "mid": "/m/06pj2k",
            "score": 0.9790179133415222,
            "topicality": 0.9790179133415222,
            "description": "Lip"
        },
        {
            "mid": "/m/037p5b",
            "score": 0.9788213968276978,
            "topicality": 0.9788213968276978,
            "description": "Cheek"
        },
        {
            "mid": "/m/014sv8",
            "score": 0.9785585403442383,
            "topicality": 0.9785585403442383,
            "description": "Eye"
        },
        {
            "mid": "/m/09g5pq",
            "score": 0.9773341417312622,
            "topicality": 0.9773341417312622,
            "description": "People"
        },
        {
            "mid": "/m/09q2t",
            "score": 0.976443886756897,
            "topicality": 0.976443886756897,
            "description": "Brown"
        },
        {
            "mid": "/m/0ds4x",
            "score": 0.9741053581237793,
            "topicality": 0.9741053581237793,
            "description": "Hairstyle"
        },
        {
            "mid": "/m/06z04",
            "score": 0.9733490943908691,
            "topicality": 0.9733490943908691,
            "description": "Skin"
        },
        {
            "mid": "/m/0f9swq",
            "score": 0.9693323969841003,
            "topicality": 0.9693323969841003,
            "description": "Chin"
        }
    ],
    "safe_search_annotations": {
        "adult": {
            "likelihood": "VERY_UNLIKELY"
        },
        "racy": {
            "likelihood": "VERY_UNLIKELY"
        },
        "spoof": {
            "likelihood": "VERY_UNLIKELY"
        },
        "medical": {
            "likelihood": "UNLIKELY"
        },
        "violence": {
            "likelihood": "UNLIKELY"
        }
    }
}