{
    "path": "../output/imgs/kittitian-women/72.jpeg",
    "search_query": "kittitian-women",
    "position": 72,
    "label_annotations": [
        {
            "mid": "/m/09j5n",
            "score": 0.9886714816093445,
            "topicality": 0.9886714816093445,
            "description": "Footwear"
        },
        {
            "mid": "/m/02p0tk3",
            "score": 0.9697598218917847,
            "topicality": 0.9697598218917847,
            "description": "Human body"
        },
        {
            "mid": "/m/01b4q9",
            "score": 0.9633197784423828,
            "topicality": 0.9633197784423828,
            "description": "Social group"
        },
        {
            "mid": "/m/01qls",
            "score": 0.9402888417243958,
            "topicality": 0.9402888417243958,
            "description": "Community"
        },
        {
            "mid": "/m/032tl",
            "score": 0.8879921436309814,
            "topicality": 0.8879921436309814,
            "description": "Fashion"
        },
        {
            "mid": "/m/02p6k8p",
            "score": 0.829755425453186,
            "topicality": 0.829755425453186,
            "description": "Bouquet"
        },
        {
            "mid": "/m/0ggjrhd",
            "score": 0.7526794672012329,
            "topicality": 0.7526794672012329,
            "description": "Flower Arranging"
        },
        {
            "mid": "/m/02hcw1",
            "score": 0.7049890160560608,
            "topicality": 0.7049890160560608,
            "description": "Floristry"
        },
        {
            "mid": "/m/0ds61d1",
            "score": 0.6905958652496338,
            "topicality": 0.6905958652496338,
            "description": "Cut flowers"
        },
        {
            "mid": "/m/016c4t",
            "score": 0.6893763542175293,
            "topicality": 0.6893763542175293,
            "description": "Ceremony"
        }
    ],
    "safe_search_annotations": {
        "adult": {
            "likelihood": "VERY_UNLIKELY"
        },
        "racy": {
            "likelihood": "VERY_UNLIKELY"
        },
        "spoof": {
            "likelihood": "VERY_UNLIKELY"
        },
        "medical": {
            "likelihood": "VERY_UNLIKELY"
        },
        "violence": {
            "likelihood": "VERY_UNLIKELY"
        }
    }
}