{
    "path": "../output/imgs/maldivian-women/71.jpeg",
    "search_query": "maldivian-women",
    "position": 71,
    "label_annotations": [
        {
            "mid": "/m/0g7xf",
            "score": 0.8576710224151611,
            "topicality": 0.8576710224151611,
            "description": "Broom"
        },
        {
            "mid": "/m/037nx6",
            "score": 0.8188338279724121,
            "topicality": 0.8188338279724121,
            "description": "Street sweeper"
        },
        {
            "mid": "/m/02tcwp",
            "score": 0.7884266376495361,
            "topicality": 0.7884266376495361,
            "description": "Trunk"
        },
        {
            "mid": "/m/0h8nt1x",
            "score": 0.7429609894752502,
            "topicality": 0.7429609894752502,
            "description": "Household supply"
        },
        {
            "mid": "/m/0hndl",
            "score": 0.6955731511116028,
            "topicality": 0.6955731511116028,
            "description": "Shade"
        },
        {
            "mid": "/m/01mxf",
            "score": 0.6897715330123901,
            "topicality": 0.6897715330123901,
            "description": "Concrete"
        },
        {
            "mid": "/m/02chd9",
            "score": 0.6686390042304993,
            "topicality": 0.6686390042304993,
            "description": "Brush"
        },
        {
            "mid": "/m/0h8ntf7",
            "score": 0.6277206540107727,
            "topicality": 0.6277206540107727,
            "description": "Household cleaning supply"
        },
        {
            "mid": "/m/01ft8k",
            "score": 0.6041879057884216,
            "topicality": 0.6041879057884216,
            "description": "Shadow"
        },
        {
            "mid": "/m/06c7cv",
            "score": 0.5011705756187439,
            "topicality": 0.5011705756187439,
            "description": "Kneeling"
        }
    ],
    "safe_search_annotations": {
        "adult": {
            "likelihood": "VERY_UNLIKELY"
        },
        "racy": {
            "likelihood": "VERY_UNLIKELY"
        },
        "spoof": {
            "likelihood": "UNLIKELY"
        },
        "medical": {
            "likelihood": "VERY_UNLIKELY"
        },
        "violence": {
            "likelihood": "UNLIKELY"
        }
    }
}