{
    "path": "../output/imgs/montenegrin-women/13.jpeg",
    "search_query": "montenegrin-women",
    "position": 13,
    "label_annotations": [
        {
            "mid": "/m/09w5r",
            "score": 0.9515347480773926,
            "topicality": 0.9515347480773926,
            "description": "Human leg"
        },
        {
            "mid": "/m/077p0h",
            "score": 0.9339554309844971,
            "topicality": 0.9339554309844971,
            "description": "Sleeveless shirt"
        },
        {
            "mid": "/m/01vm1p",
            "score": 0.9322906136512756,
            "topicality": 0.9322906136512756,
            "description": "Elbow"
        },
        {
            "mid": "/m/015c4z",
            "score": 0.9148107767105103,
            "topicality": 0.9148107767105103,
            "description": "Sitting"
        },
        {
            "mid": "/m/019swr",
            "score": 0.9024924039840698,
            "topicality": 0.9024924039840698,
            "description": "Knee"
        },
        {
            "mid": "/m/01j04m",
            "score": 0.8982246518135071,
            "topicality": 0.8982246518135071,
            "description": "Thigh"
        },
        {
            "mid": "/m/0hgn_pr",
            "score": 0.8974632024765015,
            "topicality": 0.8974632024765015,
            "description": "Active pants"
        },
        {
            "mid": "/m/01f43",
            "score": 0.8809987306594849,
            "topicality": 0.8809987306594849,
            "description": "Beauty"
        },
        {
            "mid": "/m/0hgntgw",
            "score": 0.8635064959526062,
            "topicality": 0.8635064959526062,
            "description": "Active tank"
        },
        {
            "mid": "/m/0dzdr",
            "score": 0.756228506565094,
            "topicality": 0.756228506565094,
            "description": "Chest"
        }
    ],
    "safe_search_annotations": {
        "adult": {
            "likelihood": "VERY_UNLIKELY"
        },
        "racy": {
            "likelihood": "POSSIBLE"
        },
        "spoof": {
            "likelihood": "VERY_UNLIKELY"
        },
        "medical": {
            "likelihood": "UNLIKELY"
        },
        "violence": {
            "likelihood": "VERY_UNLIKELY"
        }
    }
}