{
    "path": "../output/imgs/northern-irish-women/98.jpeg",
    "search_query": "northern-irish-women",
    "position": 98,
    "label_annotations": [
        {
            "mid": "/m/09g5pq",
            "score": 0.9771943688392639,
            "topicality": 0.9771943688392639,
            "description": "People"
        },
        {
            "mid": "/m/01b4q9",
            "score": 0.9582618474960327,
            "topicality": 0.9582618474960327,
            "description": "Social group"
        },
        {
            "mid": "/m/01nd_n",
            "score": 0.9298043847084045,
            "topicality": 0.9298043847084045,
            "description": "Protest"
        },
        {
            "mid": "/g/116c3n66l",
            "score": 0.8337715268135071,
            "topicality": 0.8337715268135071,
            "description": "Public event"
        },
        {
            "mid": "/m/0gkxy13",
            "score": 0.832682192325592,
            "topicality": 0.832682192325592,
            "description": "Handwriting"
        },
        {
            "mid": "/m/01n5jq",
            "score": 0.8295289278030396,
            "topicality": 0.8295289278030396,
            "description": "Poster"
        },
        {
            "mid": "/m/0m9cj",
            "score": 0.791469931602478,
            "topicality": 0.791469931602478,
            "description": "Banner"
        },
        {
            "mid": "/m/011s0",
            "score": 0.7731267213821411,
            "topicality": 0.7731267213821411,
            "description": "Advertising"
        },
        {
            "mid": "/m/02k88w",
            "score": 0.7673088908195496,
            "topicality": 0.7673088908195496,
            "description": "Rebellion"
        },
        {
            "mid": "/m/03120",
            "score": 0.7193504571914673,
            "topicality": 0.7193504571914673,
            "description": "Flag"
        }
    ],
    "safe_search_annotations": {
        "adult": {
            "likelihood": "VERY_UNLIKELY"
        },
        "racy": {
            "likelihood": "VERY_UNLIKELY"
        },
        "spoof": {
            "likelihood": "VERY_UNLIKELY"
        },
        "medical": {
            "likelihood": "VERY_UNLIKELY"
        },
        "violence": {
            "likelihood": "UNLIKELY"
        }
    }
}