{
    "path": "../output/imgs/north-korean-women/56.jpeg",
    "search_query": "north-korean-women",
    "position": 56,
    "label_annotations": [
        {
            "mid": "/m/086mh",
            "score": 0.9707590341567993,
            "topicality": 0.9707590341567993,
            "description": "Winter"
        },
        {
            "mid": "/m/02p0tk3",
            "score": 0.9689914584159851,
            "topicality": 0.9689914584159851,
            "description": "Human body"
        },
        {
            "mid": "/m/0408t8_",
            "score": 0.895976185798645,
            "topicality": 0.895976185798645,
            "description": "Street fashion"
        },
        {
            "mid": "/m/02q2kc3",
            "score": 0.8464425206184387,
            "topicality": 0.8464425206184387,
            "description": "Vehicle door"
        },
        {
            "mid": "/m/02h19r",
            "score": 0.7355870008468628,
            "topicality": 0.7355870008468628,
            "description": "Scarf"
        },
        {
            "mid": "/m/088l6h",
            "score": 0.7270121574401855,
            "topicality": 0.7270121574401855,
            "description": "Family car"
        },
        {
            "mid": "/m/03vnt4",
            "score": 0.6851553916931152,
            "topicality": 0.6851553916931152,
            "description": "Mid-size car"
        },
        {
            "mid": "/m/03tvvb",
            "score": 0.5480878949165344,
            "topicality": 0.5480878949165344,
            "description": "Overcoat"
        }
    ],
    "safe_search_annotations": {
        "adult": {
            "likelihood": "UNLIKELY"
        },
        "racy": {
            "likelihood": "VERY_UNLIKELY"
        },
        "spoof": {
            "likelihood": "VERY_UNLIKELY"
        },
        "medical": {
            "likelihood": "VERY_UNLIKELY"
        },
        "violence": {
            "likelihood": "UNLIKELY"
        }
    }
}