{
    "path": "../output/imgs/saint-lucian-women/32.jpeg",
    "search_query": "saint-lucian-women",
    "position": 32,
    "label_annotations": [
        {
            "mid": "/m/0j272k5",
            "score": 0.9900864958763123,
            "topicality": 0.9900864958763123,
            "description": "Eyewear"
        },
        {
            "mid": "/m/0h8jxfl",
            "score": 0.9816900491714478,
            "topicality": 0.9816900491714478,
            "description": "Vision care"
        },
        {
            "mid": "/m/01g5v",
            "score": 0.9803432822227478,
            "topicality": 0.9803432822227478,
            "description": "Blue"
        },
        {
            "mid": "/m/06pj2k",
            "score": 0.978999674320221,
            "topicality": 0.978999674320221,
            "description": "Lip"
        },
        {
            "mid": "/m/0jyfg",
            "score": 0.9788256883621216,
            "topicality": 0.9788256883621216,
            "description": "Glasses"
        },
        {
            "mid": "/m/037p5b",
            "score": 0.9785216450691223,
            "topicality": 0.9785216450691223,
            "description": "Cheek"
        },
        {
            "mid": "/m/0f9swq",
            "score": 0.9692661166191101,
            "topicality": 0.9692661166191101,
            "description": "Chin"
        },
        {
            "mid": "/m/025kyy",
            "score": 0.9681846499443054,
            "topicality": 0.9681846499443054,
            "description": "Forehead"
        },
        {
            "mid": "/m/027n3_",
            "score": 0.9639064073562622,
            "topicality": 0.9639064073562622,
            "description": "Eyebrow"
        },
        {
            "mid": "/m/016pp7",
            "score": 0.9417750239372253,
            "topicality": 0.9417750239372253,
            "description": "Happy"
        }
    ],
    "safe_search_annotations": {
        "adult": {
            "likelihood": "VERY_UNLIKELY"
        },
        "racy": {
            "likelihood": "VERY_UNLIKELY"
        },
        "spoof": {
            "likelihood": "VERY_UNLIKELY"
        },
        "medical": {
            "likelihood": "VERY_UNLIKELY"
        },
        "violence": {
            "likelihood": "VERY_UNLIKELY"
        }
    }
}