{
    "path": "../output/imgs/samoan-women/57.jpeg",
    "search_query": "samoan-women",
    "position": 57,
    "label_annotations": [
        {
            "mid": "/m/0ds99lh",
            "score": 0.9768338799476624,
            "topicality": 0.9768338799476624,
            "description": "Fun"
        },
        {
            "mid": "/m/09g5pq",
            "score": 0.9766259789466858,
            "topicality": 0.9766259789466858,
            "description": "People"
        },
        {
            "mid": "/m/01b4q9",
            "score": 0.9686310887336731,
            "topicality": 0.9686310887336731,
            "description": "Social group"
        },
        {
            "mid": "/m/016pp7",
            "score": 0.9416404366493225,
            "topicality": 0.9416404366493225,
            "description": "Happy"
        },
        {
            "mid": "/j/3gbwgn",
            "score": 0.938552975654602,
            "topicality": 0.938552975654602,
            "description": "People in nature"
        },
        {
            "mid": "/m/07bxq",
            "score": 0.9212104678153992,
            "topicality": 0.9212104678153992,
            "description": "Tourism"
        },
        {
            "mid": "/m/014dsx",
            "score": 0.8809940814971924,
            "topicality": 0.8809940814971924,
            "description": "Travel"
        },
        {
            "mid": "/m/031974",
            "score": 0.8453060984611511,
            "topicality": 0.8453060984611511,
            "description": "Waist"
        },
        {
            "mid": "/j/148skd",
            "score": 0.8282477855682373,
            "topicality": 0.8282477855682373,
            "description": "People on beach"
        },
        {
            "mid": "/m/099fz",
            "score": 0.6559572219848633,
            "topicality": 0.6559572219848633,
            "description": "Sand"
        }
    ],
    "safe_search_annotations": {
        "adult": {
            "likelihood": "VERY_UNLIKELY"
        },
        "racy": {
            "likelihood": "VERY_UNLIKELY"
        },
        "spoof": {
            "likelihood": "VERY_UNLIKELY"
        },
        "medical": {
            "likelihood": "VERY_UNLIKELY"
        },
        "violence": {
            "likelihood": "VERY_UNLIKELY"
        }
    }
}