{
    "path": "../output/imgs/solomon-island-women/4.jpeg",
    "search_query": "solomon-island-women",
    "position": 4,
    "label_annotations": [
        {
            "mid": "/m/0dzct",
            "score": 0.9888705611228943,
            "topicality": 0.9888705611228943,
            "description": "Face"
        },
        {
            "mid": "/m/0k0pj",
            "score": 0.9837234020233154,
            "topicality": 0.9837234020233154,
            "description": "Nose"
        },
        {
            "mid": "/m/019nj4",
            "score": 0.9798487424850464,
            "topicality": 0.9798487424850464,
            "description": "Smile"
        },
        {
            "mid": "/m/0283dt1",
            "score": 0.978538453578949,
            "topicality": 0.978538453578949,
            "description": "Mouth"
        },
        {
            "mid": "/m/09g5pq",
            "score": 0.977325439453125,
            "topicality": 0.977325439453125,
            "description": "People"
        },
        {
            "mid": "/m/06z04",
            "score": 0.9702228903770447,
            "topicality": 0.9702228903770447,
            "description": "Skin"
        },
        {
            "mid": "/m/01ssh5",
            "score": 0.9654130339622498,
            "topicality": 0.9654130339622498,
            "description": "Shoulder"
        },
        {
            "mid": "/m/016pp7",
            "score": 0.9483028650283813,
            "topicality": 0.9483028650283813,
            "description": "Happy"
        },
        {
            "mid": "/m/01qls",
            "score": 0.9401974678039551,
            "topicality": 0.9401974678039551,
            "description": "Community"
        },
        {
            "mid": "/m/01k74n",
            "score": 0.9344747066497803,
            "topicality": 0.9344747066497803,
            "description": "Facial expression"
        }
    ],
    "safe_search_annotations": {
        "adult": {
            "likelihood": "VERY_UNLIKELY"
        },
        "racy": {
            "likelihood": "UNLIKELY"
        },
        "spoof": {
            "likelihood": "VERY_UNLIKELY"
        },
        "medical": {
            "likelihood": "UNLIKELY"
        },
        "violence": {
            "likelihood": "VERY_UNLIKELY"
        }
    }
}