{
    "path": "../output/imgs/south-african-women/51.jpeg",
    "search_query": "south-african-women",
    "position": 51,
    "label_annotations": [
        {
            "mid": "/m/03q69",
            "score": 0.9897587895393372,
            "topicality": 0.9897587895393372,
            "description": "Hair"
        },
        {
            "mid": "/m/0dzct",
            "score": 0.9895330667495728,
            "topicality": 0.9895330667495728,
            "description": "Face"
        },
        {
            "mid": "/m/04hgtk",
            "score": 0.988368570804596,
            "topicality": 0.988368570804596,
            "description": "Head"
        },
        {
            "mid": "/m/0k0pj",
            "score": 0.9844151139259338,
            "topicality": 0.9844151139259338,
            "description": "Nose"
        },
        {
            "mid": "/m/09g5pq",
            "score": 0.9773876667022705,
            "topicality": 0.9773876667022705,
            "description": "People"
        },
        {
            "mid": "/m/03qtwd",
            "score": 0.9727648496627808,
            "topicality": 0.9727648496627808,
            "description": "Crowd"
        },
        {
            "mid": "/m/0k65p",
            "score": 0.955780029296875,
            "topicality": 0.955780029296875,
            "description": "Hand"
        },
        {
            "mid": "/m/02dl1y",
            "score": 0.9489853382110596,
            "topicality": 0.9489853382110596,
            "description": "Hat"
        },
        {
            "mid": "/m/04rky",
            "score": 0.947499692440033,
            "topicality": 0.947499692440033,
            "description": "Mammal"
        },
        {
            "mid": "/m/01nd_n",
            "score": 0.8665335178375244,
            "topicality": 0.8665335178375244,
            "description": "Protest"
        }
    ],
    "safe_search_annotations": {
        "adult": {
            "likelihood": "VERY_UNLIKELY"
        },
        "racy": {
            "likelihood": "UNLIKELY"
        },
        "spoof": {
            "likelihood": "UNLIKELY"
        },
        "medical": {
            "likelihood": "VERY_UNLIKELY"
        },
        "violence": {
            "likelihood": "UNLIKELY"
        }
    }
}