{
    "path": "../output/imgs/uzbekistani-women/35.jpeg",
    "search_query": "uzbekistani-women",
    "position": 35,
    "label_annotations": [
        {
            "mid": "/m/0dzct",
            "score": 0.9888332486152649,
            "topicality": 0.9888332486152649,
            "description": "Face"
        },
        {
            "mid": "/m/0h8mhzd",
            "score": 0.9847203493118286,
            "topicality": 0.9847203493118286,
            "description": "Sports uniform"
        },
        {
            "mid": "/m/018xm",
            "score": 0.9841756820678711,
            "topicality": 0.9841756820678711,
            "description": "Ball"
        },
        {
            "mid": "/m/025xryy",
            "score": 0.9744162559509277,
            "topicality": 0.9744162559509277,
            "description": "Sportswear"
        },
        {
            "mid": "/m/05y5lj",
            "score": 0.970740556716919,
            "topicality": 0.970740556716919,
            "description": "Sports equipment"
        },
        {
            "mid": "/m/02h00q",
            "score": 0.9670453071594238,
            "topicality": 0.9670453071594238,
            "description": "Jersey"
        },
        {
            "mid": "/m/077p0h",
            "score": 0.9647988080978394,
            "topicality": 0.9647988080978394,
            "description": "Sleeveless shirt"
        },
        {
            "mid": "/m/03x045",
            "score": 0.9561982750892639,
            "topicality": 0.9561982750892639,
            "description": "Team sport"
        },
        {
            "mid": "/m/09jfs",
            "score": 0.9467788338661194,
            "topicality": 0.9467788338661194,
            "description": "Uniform"
        },
        {
            "mid": "/m/020m7t",
            "score": 0.942905604839325,
            "topicality": 0.942905604839325,
            "description": "Ball game"
        }
    ],
    "safe_search_annotations": {
        "adult": {
            "likelihood": "VERY_UNLIKELY"
        },
        "racy": {
            "likelihood": "VERY_UNLIKELY"
        },
        "spoof": {
            "likelihood": "VERY_UNLIKELY"
        },
        "medical": {
            "likelihood": "VERY_UNLIKELY"
        },
        "violence": {
            "likelihood": "VERY_UNLIKELY"
        }
    }
}